[{"id":1,"name":"Valera","posts":[{"id":8,"content":"This is a post text. ","tags":[{"id":25,"name":"label"}],"status":"ACTIVE"}]},{"id":3,"name":"Valera","posts":[{"id":10,"content":"This is a post text. ","tags":[{"id":26,"name":"Label"}],"status":"ACTIVE"}]},{"id":4,"name":"Valera","posts":[]},{"id":5,"name":"Sergo","posts":[{"id":12,"content":"dddfddff","tags":[{"id":27,"name":"qqq"},{"id":28,"name":"222"}],"status":"ACTIVE"},{"id":13,"content":"dddddffgg","tags":[],"status":"ACTIVE"},{"id":14,"content":"ssdfdds","tags":[{"id":29,"name":"eeee"}],"status":"ACTIVE"}]},{"id":6,"name":"d","posts":[]},{"id":7,"name":"sss","posts":[]}]